ally_ai_chroma_visualise/ChromaEmbeddingsVisualisor.py
ally_ai_chroma_visualise/EmbeddingsVisualisor.py
ally_ai_chroma_visualise/__init__.py
ally_ai_chroma_visualise-0.1.0.dist-info/LICENSE
ally_ai_chroma_visualise-0.1.0.dist-info/METADATA
ally_ai_chroma_visualise-0.1.0.dist-info/WHEEL
ally_ai_chroma_visualise-0.1.0.dist-info/top_level.txt
ally_ai_chroma_visualise-0.1.0.dist-info/RECORD
